MANIFEST.in
README.md
requirements.txt
setup.py
bmd_py.egg-info/PKG-INFO
bmd_py.egg-info/SOURCES.txt
bmd_py.egg-info/dependency_links.txt
bmd_py.egg-info/requires.txt
bmd_py.egg-info/top_level.txt
src/bmd.py