Metadata-Version: 2.1
Name: bmd-py
Version: 1.1.0
Summary: Change scripts into Markdown documentation
Home-page: https://git.sr.ht/~vlnk/bmd
Author: vlnk
Author-email: vlnk@protonmail.com
License: GPLv3+
Platform: UNKNOWN
Requires-Python: >=3.7.8
